{"version":1,"resource":"file:///root/Desktop/Environments/Expense/expense_tracker/expense/views.py","entries":[{"id":"HwtD.py","timestamp":1741361440287},{"id":"HE3J.py","timestamp":1741361483843},{"id":"qY3U.py","timestamp":1741361509619},{"id":"F827.py","timestamp":1741361523399},{"id":"rbTt.py","timestamp":1741361943961},{"id":"g4oI.py","timestamp":1741363254069},{"id":"dNmI.py","timestamp":1741363267025},{"id":"0uMH.py","timestamp":1741363285186},{"id":"2hBk.py","timestamp":1741363304358},{"id":"rMEG.py","timestamp":1741363356590},{"id":"ldxz.py","timestamp":1741363375282},{"id":"FC2c.py","timestamp":1741363390022},{"id":"HOq3.py","timestamp":1741363402811},{"id":"Qj84.py","timestamp":1741364029774},{"id":"788F.py","timestamp":1741364051923},{"id":"jwkg.py","timestamp":1741364495147},{"id":"9lmJ.py","timestamp":1741366622442},{"id":"aTEK.py","timestamp":1741366867868},{"id":"atTF.py","source":"undoRedo.source","timestamp":1741366872440},{"id":"RH4v.py","timestamp":1741366889069},{"id":"MH15.py","timestamp":1741366905313}]}