{"version":1,"resource":"file:///root/Desktop/Environments/Expense/expense_tracker/expense_tracker/settings.py","entries":[{"id":"18an.py","timestamp":1741360709637},{"id":"Gp7x.py","timestamp":1741365616356},{"id":"9EGl.py","timestamp":1741366976711},{"id":"zCdc.py","timestamp":1741371400403},{"id":"nsny.py","timestamp":1741372111672},{"id":"j8Dw.py","timestamp":1741372129564},{"id":"J8uA.py","timestamp":1744547307777},{"id":"V7Bc.py","timestamp":1744547362771},{"id":"RNST.py","timestamp":1744547402301},{"id":"zHTm.py","timestamp":1744547682037},{"id":"vzYT.py","source":"undoRedo.source","timestamp":1744547732671},{"id":"FTOh.py","timestamp":1744556747307},{"id":"rhxX.py","timestamp":1744640675264},{"id":"2wWi.py","timestamp":1744640710197},{"id":"tzfM.py","timestamp":1744640809252},{"id":"D9zZ.py","source":"undoRedo.source","timestamp":1744640812196},{"id":"YjSF.py","timestamp":1744640816024},{"id":"Zg7H.py","timestamp":1744640862986},{"id":"4IGr.py","timestamp":1744640878074},{"id":"zTNB.py","source":"undoRedo.source","timestamp":1744640879810},{"id":"5hCV.py","timestamp":1744640915947},{"id":"3BTP.py","timestamp":1744640956716},{"id":"WNjY.py","timestamp":1744640970173},{"id":"v2YI.py","timestamp":1744640985485},{"id":"LL8R.py","timestamp":1744641042559},{"id":"99wX.py","timestamp":1744642512576},{"id":"U4EA.py","timestamp":1744642533073},{"id":"nGZR.py","timestamp":1744642579002}]}